LICENSE
README.md
pyproject.toml
flask_tdg_cyberx/__init__.py
flask_tdg_cyberx.egg-info/PKG-INFO
flask_tdg_cyberx.egg-info/SOURCES.txt
flask_tdg_cyberx.egg-info/dependency_links.txt
flask_tdg_cyberx.egg-info/top_level.txt