Metadata-Version: 2.4
Name: flask_tdg_cyberx
Version: 3.300.41
Summary: play CTF
Author-email: UkidChangsan <ukid@mit.edu>
License: MIT
Classifier: Programming Language :: Python :: 3
Classifier: License :: OSI Approved :: MIT License
Classifier: Operating System :: OS Independent
Requires-Python: >=3.7
License-File: LICENSE
Dynamic: license-file
